circuitpython_nrf24l01/__init__.py
circuitpython_nrf24l01/fake_ble.py
circuitpython_nrf24l01/rf24.py
circuitpython_nrf24l01/rf24_lite.py
circuitpython_nrf24l01/rf24_mesh.py
circuitpython_nrf24l01/rf24_network.py
circuitpython_nrf24l01/network/__init__.py
circuitpython_nrf24l01/network/constants.py
circuitpython_nrf24l01/network/mixins.py
circuitpython_nrf24l01/network/structs.py
circuitpython_nrf24l01/wrapper/__init__.py
circuitpython_nrf24l01/wrapper/cpy_spidev.py
circuitpython_nrf24l01-2.1.6.dist-info/licenses/LICENSE
circuitpython_nrf24l01-2.1.6.dist-info/METADATA
circuitpython_nrf24l01-2.1.6.dist-info/WHEEL
circuitpython_nrf24l01-2.1.6.dist-info/top_level.txt
circuitpython_nrf24l01-2.1.6.dist-info/RECORD
