Metadata-Version: 2.4
Name: circuitpython-nrf24l01
Version: 2.1.6
Summary: CircuitPython driver library for the nRF24L01 transceiver
Author-email: Brendan Doherty <2bndy5@gmail.com>
License: MIT
Project-URL: Documentation, https://circuitpython-nrf24l01.readthedocs.io
Project-URL: Source, https://github.com/2bndy5/CircuitPython_nRF24L01
Project-URL: Tracker, https://github.com/2bndy5/CircuitPython_nRF24L01/issues
Keywords: blinka,circuitpython,nrf24l01,nrf24l01+,raspberrypi,driver,radio,transceiver
Classifier: Development Status :: 5 - Production/Stable
Classifier: Intended Audience :: Developers
Classifier: Topic :: Software Development :: Libraries
Classifier: Topic :: System :: Hardware
Classifier: License :: OSI Approved :: MIT License
Classifier: Programming Language :: Python :: 3
Classifier: Programming Language :: Python :: 3.7
Classifier: Programming Language :: Python :: 3.8
Classifier: Programming Language :: Python :: 3.9
Classifier: Programming Language :: Python :: 3.10
Requires-Python: >=3.7
License-File: LICENSE
Requires-Dist: Adafruit-Blinka
Requires-Dist: adafruit-circuitpython-busdevice
Requires-Dist: spidev; sys_platform == "linux" and (platform_machine == "armv7l" or platform_machine == "armv6l" or platform_machine == "aarch64")
Requires-Dist: typing-extensions
Dynamic: license-file
